[
    {
        "Data stipula": "", 
        "CIG": "5511366B17", 
        "ID contratto": "", 
        "Sigla grande progetto": "G.P.P.", 
        "Operatore capogruppo": "", 
        "Tipo gara": "Sistema dinamico di acquisizione", 
        "Importo contratto": "", 
        "Longitudine": "14.4989344", 
        "Tipologia": "Sistemi tecnologici", 
        "Durata giorni": "60", 
        "Aliquota forfettaria": "", 
        "Piano": "Piano di rafforzamento tecnologico e di capacity building", 
        "ID conti appaltatore": "", 
        "Num ditte invitate": "0", 
        "Oggetto": "", 
        "Importo servizi": "0", 
        "Data risoluzione": "", 
        "CUP": "F69J13000530006", 
        "Num perizia": "36298", 
        "Data prevista inizio lavori": "", 
        "Sotto riserva di legge": "", 
        "Data inizio validita": "", 
        "Data prevista fine lavori": "", 
        "Dettaglio localizzazione": "", 
        "Latitudine": "40.7461572", 
        "Importo lavori": "0.0", 
        "Data pubblicazione": "2013-12-13", 
        "Importo totale": "990000", 
        "Data fine validita": "", 
        "ID bando": "44636", 
        "Importo base asta": "110200", 
        "Operatori associati": "", 
        "ID progetto": "44631", 
        "Oneri della sicurezza": "0", 
        "Progetto": "Acquisto attrezzature hardware e software", 
        "IVA": "", 
        "Importo forniture": "110200", 
        "Protocollo determina": "225", 
        "Somme a disposizione dell'amministrazione": "0", 
        "RUP": "Luisa Rapone"
    }, 
    {
        "Data stipula": "2013-05-14", 
        "CIG": "41064963B3", 
        "ID contratto": "21350", 
        "Sigla grande progetto": "G.P.P.", 
        "Operatore capogruppo": "Perillo Costruzioni Generali", 
        "Tipo gara": "Procedura ristretta", 
        "Importo contratto": "304635.9", 
        "Longitudine": "14.4894648", 
        "Tipologia": "Restauro architettonico", 
        "Durata giorni": "370", 
        "Aliquota forfettaria": "", 
        "Piano": "Piano delle opere", 
        "ID conti appaltatore": "21352,48827,55528", 
        "Num ditte invitate": "33", 
        "Oggetto": "", 
        "Importo servizi": "0", 
        "Data risoluzione": "", 
        "CUP": "F64B12000120001", 
        "Num perizia": "14", 
        "Data prevista inizio lavori": "2013-02-01", 
        "Sotto riserva di legge": "true", 
        "Data inizio validita": "", 
        "Data prevista fine lavori": "2014-02-18", 
        "Dettaglio localizzazione": "Civico 2", 
        "Latitudine": "40.7505464", 
        "Importo lavori": "455952.86", 
        "Data pubblicazione": "2012-04-03", 
        "Importo totale": "750000", 
        "Data fine validita": "", 
        "ID bando": "14403", 
        "Importo base asta": "563161.18", 
        "Operatori associati": "", 
        "ID progetto": "14400", 
        "Oneri della sicurezza": "8539.11", 
        "Progetto": "Consolidamento e restauro delle strutture della Casa del Criptoportico", 
        "IVA": "63973.54", 
        "Importo forniture": "0", 
        "Protocollo determina": "", 
        "Somme a disposizione dell'amministrazione": "98669.21", 
        "RUP": "Ernesto De Carolis"
    }, 
    {
        "Data stipula": "2014-06-17", 
        "CIG": "5472771180", 
        "ID contratto": "56011", 
        "Sigla grande progetto": "G.P.P.", 
        "Operatore capogruppo": "Geomed Srl Geoarcheologia e Geologia Ambientale", 
        "Tipo gara": "Procedura ai sensi art. 204 comma 1 e art. 122 comma 7 del Dlgs163/2006.", 
        "Importo contratto": "", 
        "Longitudine": "14.4989344", 
        "Tipologia": "Diagnosi e monitoraggio", 
        "Durata giorni": "60", 
        "Aliquota forfettaria": "4436", 
        "Piano": "Piano della conoscenza", 
        "ID conti appaltatore": "56012", 
        "Num ditte invitate": "8", 
        "Oggetto": "", 
        "Importo servizi": "39163.31", 
        "Data risoluzione": "", 
        "CUP": "F63D13000720006", 
        "Num perizia": "0", 
        "Data prevista inizio lavori": "", 
        "Sotto riserva di legge": "true", 
        "Data inizio validita": "", 
        "Data prevista fine lavori": "", 
        "Dettaglio localizzazione": "", 
        "Latitudine": "40.7461572", 
        "Importo lavori": "77037.78", 
        "Data pubblicazione": "", 
        "Importo totale": "18236555", 
        "Data fine validita": "", 
        "ID bando": "55542", 
        "Importo base asta": "134257.95", 
        "Operatori associati": "", 
        "ID progetto": "55532", 
        "Oneri della sicurezza": "13620.86", 
        "Progetto": "Indagini geognostiche e studi per la mitigazione del rischio idrogeologico dei pianori non scavati e dei fonti di scavo delle Regiones I, IV e V e del banco roccioso del fronte sud della Regio VIII", 
        "IVA": "", 
        "Importo forniture": "0", 
        "Protocollo determina": "Decreto n° 230", 
        "Somme a disposizione dell'amministrazione": "15706.22", 
        "RUP": "Grete Stefani"
    }, 
    {
        "Data stipula": "2013-11-13", 
        "CIG": "41068675DB", 
        "ID contratto": "33273", 
        "Sigla grande progetto": "G.P.P.", 
        "Operatore capogruppo": "Forte Costruzioni e Restauri", 
        "Tipo gara": "Procedura ristretta", 
        "Importo contratto": "585381.36", 
        "Longitudine": "14.4834559", 
        "Tipologia": "Restauro architettonico", 
        "Durata giorni": "550", 
        "Aliquota forfettaria": "", 
        "Piano": "Piano delle opere", 
        "ID conti appaltatore": "31375", 
        "Num ditte invitate": "33", 
        "Oggetto": "", 
        "Importo servizi": "0", 
        "Data risoluzione": "", 
        "CUP": "F64B12000090001", 
        "Num perizia": "11", 
        "Data prevista inizio lavori": "2013-08-05", 
        "Sotto riserva di legge": "true", 
        "Data inizio validita": "", 
        "Data prevista fine lavori": "2015-02-06", 
        "Dettaglio localizzazione": "Casa del Marinaio", 
        "Latitudine": "40.7491808", 
        "Importo lavori": "949232.76", 
        "Data pubblicazione": "2012-04-13", 
        "Importo totale": "101253581", 
        "Data fine validita": "", 
        "ID bando": "30336", 
        "Importo base asta": "1012535.81", 
        "Operatori associati": "", 
        "ID progetto": "30331", 
        "Oneri della sicurezza": "29311.55", 
        "Progetto": "Lavori di consolidamento e restauro delle strutture della Casa del Marinaio", 
        "IVA": "122930.09", 
        "Importo forniture": "0", 
        "Protocollo determina": "13207", 
        "Somme a disposizione dell'amministrazione": "33991.5", 
        "RUP": "Ernesto De Carolis"
    }, 
    {
        "Data stipula": "2013-06-27", 
        "CIG": "4106680B88", 
        "ID contratto": "30046", 
        "Sigla grande progetto": "", 
        "Operatore capogruppo": "Perillo Costruzioni Generali", 
        "Tipo gara": "Procedura ristretta", 
        "Importo contratto": "572085.11", 
        "Longitudine": "14.4869097", 
        "Tipologia": "Restauro architettonico", 
        "Durata giorni": "730", 
        "Aliquota forfettaria": "0", 
        "Piano": "Piano delle opere", 
        "ID conti appaltatore": "21352,48827,55528", 
        "Num ditte invitate": "36", 
        "Oggetto": "", 
        "Importo servizi": "0", 
        "Data risoluzione": "", 
        "CUP": "F64B12000110001", 
        "Num perizia": "10", 
        "Data prevista inizio lavori": "2013-06-28", 
        "Sotto riserva di legge": "false", 
        "Data inizio validita": "", 
        "Data prevista fine lavori": "2015-06-28", 
        "Dettaglio localizzazione": "", 
        "Latitudine": "40.7501216", 
        "Importo lavori": "1221549.09", 
        "Data pubblicazione": "2012-04-02", 
        "Importo totale": "177814907", 
        "Data fine validita": "", 
        "ID bando": "13804", 
        "Importo base asta": "1243326.33", 
        "Operatori associati": "", 
        "ID progetto": "13802", 
        "Oneri della sicurezza": "21777.26", 
        "Progetto": "Lavori di consolidamento e restauro delle strutture della Casa di Sirico", 
        "IVA": "", 
        "Importo forniture": "0", 
        "Protocollo determina": "13210/2012", 
        "Somme a disposizione dell'amministrazione": "217953.89", 
        "RUP": "Ernesto De Carolis"
    }, 
    {
        "Data stipula": "2014-03-20", 
        "CIG": "46223167d3", 
        "ID contratto": "48828", 
        "Sigla grande progetto": "G.P.P.", 
        "Operatore capogruppo": "Perillo Costruzioni Generali", 
        "Tipo gara": "Procedura aperta", 
        "Importo contratto": "", 
        "Longitudine": "14.4989344", 
        "Tipologia": "Messa in sicurezza", 
        "Durata giorni": "360", 
        "Aliquota forfettaria": "26906.4", 
        "Piano": "Piano delle opere", 
        "ID conti appaltatore": "21352,48827,55528", 
        "Num ditte invitate": "0", 
        "Oggetto": "", 
        "Importo servizi": "0", 
        "Data risoluzione": "", 
        "CUP": "F69G12000090006", 
        "Num perizia": "1", 
        "Data prevista inizio lavori": "", 
        "Sotto riserva di legge": "true", 
        "Data inizio validita": "", 
        "Data prevista fine lavori": "", 
        "Dettaglio localizzazione": "", 
        "Latitudine": "40.7461572", 
        "Importo lavori": "1995224.42", 
        "Data pubblicazione": "2012-11-09", 
        "Importo totale": "209725678", 
        "Data fine validita": "", 
        "ID bando": "16225", 
        "Importo base asta": "1995224.42", 
        "Operatori associati": "", 
        "ID progetto": "16214", 
        "Oneri della sicurezza": "75125.96", 
        "Progetto": "Lavori di messa in sicurezza previo assetto idrogeologico dei terreni demaniali a confine area di scavo (III – IX)", 
        "IVA": "", 
        "Importo forniture": "0", 
        "Protocollo determina": "", 
        "Somme a disposizione dell'amministrazione": "-1", 
        "RUP": "Bruno Sammarco"
    }, 
    {
        "Data stipula": "2014-06-16", 
        "CIG": "51694805D8", 
        "ID contratto": "55927", 
        "Sigla grande progetto": "G.P.P.", 
        "Operatore capogruppo": "Perillo Costruzioni Generali", 
        "Tipo gara": "Affidamento in unico lotto dell’appalto misto, ai sensi degli artt. 14 e 15 del D.lgs.163/2006, di lavori e dei servizi", 
        "Importo contratto": "", 
        "Longitudine": "14.4840964", 
        "Tipologia": "Messa in sicurezza", 
        "Durata giorni": "513", 
        "Aliquota forfettaria": "38467.09", 
        "Piano": "Piano delle opere", 
        "ID conti appaltatore": "21352,48827,55528", 
        "Num ditte invitate": "0", 
        "Oggetto": "Affidamento in unico lotto dell’appalto misto, ai sensi degli artt. 14 e 15 del D.lgs.163/2006, di lavori e dei servizi per i “Lavori di messa in sicurezza Regio VI – Pompei Scavi – Intervento n°VI” - CUP: F66D12000440006", 
        "Importo servizi": "151679.67", 
        "Data risoluzione": "", 
        "CUP": "F66D12000440006", 
        "Num perizia": "6", 
        "Data prevista inizio lavori": "", 
        "Sotto riserva di legge": "true", 
        "Data inizio validita": "", 
        "Data prevista fine lavori": "", 
        "Dettaglio localizzazione": "", 
        "Latitudine": "40.7516818", 
        "Importo lavori": "2636319.52", 
        "Data pubblicazione": "2013-07-18", 
        "Importo totale": "436218933", 
        "Data fine validita": "", 
        "ID bando": "47940", 
        "Importo base asta": "3605115.15", 
        "Operatori associati": "ATRAMENTUM", 
        "ID progetto": "47938", 
        "Oneri della sicurezza": "174869.34", 
        "Progetto": "Lavori di messa in sicurezza Regio VI – Pompei Scavi – Intervento n°VI", 
        "IVA": "", 
        "Importo forniture": "0", 
        "Protocollo determina": "", 
        "Somme a disposizione dell'amministrazione": "656951.77", 
        "RUP": "Valerio Papaccio"
    }, 
    {
        "Data stipula": "", 
        "CIG": "5169367897", 
        "ID contratto": "", 
        "Sigla grande progetto": "G.P.P.", 
        "Operatore capogruppo": "", 
        "Tipo gara": "Procedura aperta", 
        "Importo contratto": "", 
        "Longitudine": "14.4845957", 
        "Tipologia": "Messa in sicurezza", 
        "Durata giorni": "510", 
        "Aliquota forfettaria": "", 
        "Piano": "Piano delle opere", 
        "ID conti appaltatore": "", 
        "Num ditte invitate": "0", 
        "Oggetto": "Affidamento in unico lotto dell'appalto misto di lavori e servizi", 
        "Importo servizi": "344528.14", 
        "Data risoluzione": "", 
        "CUP": "F64B13000310006", 
        "Num perizia": "7", 
        "Data prevista inizio lavori": "", 
        "Sotto riserva di legge": "", 
        "Data inizio validita": "", 
        "Data prevista fine lavori": "", 
        "Dettaglio localizzazione": "", 
        "Latitudine": "40.7501985", 
        "Importo lavori": "3276944.04", 
        "Data pubblicazione": "2013-07-19", 
        "Importo totale": "", 
        "Data fine validita": "", 
        "ID bando": "47753", 
        "Importo base asta": "3997358.3", 
        "Operatori associati": "", 
        "ID progetto": "47672", 
        "Oneri della sicurezza": "339908", 
        "Progetto": "Lavori di messa in sicurezza Regio VII in Pompei Scavi.", 
        "IVA": "", 
        "Importo forniture": "0", 
        "Protocollo determina": "", 
        "Somme a disposizione dell'amministrazione": "0", 
        "RUP": "Immacolata Bergamasco"
    }, 
    {
        "Data stipula": "", 
        "CIG": "5254237D86", 
        "ID contratto": "", 
        "Sigla grande progetto": "G.P.P.", 
        "Operatore capogruppo": "", 
        "Tipo gara": "Procedura aperta", 
        "Importo contratto": "", 
        "Longitudine": "14.4843038", 
        "Tipologia": "Restauro architettonico", 
        "Durata giorni": "420", 
        "Aliquota forfettaria": "27392.96", 
        "Piano": "Piano delle opere", 
        "ID conti appaltatore": "", 
        "Num ditte invitate": "0", 
        "Oggetto": "Affidamento in un unico lotto dei \"Lavori di restauro dell'Insula 15, regio VII in Pompei scavi - Intervento n° C\"", 
        "Importo servizi": "0", 
        "Data risoluzione": "", 
        "CUP": "F68I13000080006", 
        "Num perizia": "Intervento n° C", 
        "Data prevista inizio lavori": "", 
        "Sotto riserva di legge": "", 
        "Data inizio validita": "", 
        "Data prevista fine lavori": "", 
        "Dettaglio localizzazione": "", 
        "Latitudine": "40.7502499", 
        "Importo lavori": "477674.81", 
        "Data pubblicazione": "", 
        "Importo totale": "53050264", 
        "Data fine validita": "", 
        "ID bando": "55531", 
        "Importo base asta": "530502.64", 
        "Operatori associati": "", 
        "ID progetto": "55530", 
        "Oneri della sicurezza": "25434.87", 
        "Progetto": "Lavori di restauro dell'Insula 15, regio VII in Pompei scavi - Intervento n° C", 
        "IVA": "", 
        "Importo forniture": "0", 
        "Protocollo determina": "", 
        "Somme a disposizione dell'amministrazione": "0", 
        "RUP": "Ernesto De Carolis"
    }, 
    {
        "Data stipula": "", 
        "CIG": "52070322BD", 
        "ID contratto": "", 
        "Sigla grande progetto": "G.P.P.", 
        "Operatore capogruppo": "", 
        "Tipo gara": "Procedura aperta", 
        "Importo contratto": "", 
        "Longitudine": "14.4835727", 
        "Tipologia": "Messa in sicurezza", 
        "Durata giorni": "180", 
        "Aliquota forfettaria": "13308", 
        "Piano": "Piano delle opere", 
        "ID conti appaltatore": "", 
        "Num ditte invitate": "0", 
        "Oggetto": "Lavori di ripristino e di consolidamento delle strutture della casa della Fontana Piccola – Pompei Scavi – Intervento n° 26 -", 
        "Importo servizi": "19571.47", 
        "Data risoluzione": "", 
        "CUP": "F68I11000120007", 
        "Num perizia": "26", 
        "Data prevista inizio lavori": "", 
        "Sotto riserva di legge": "", 
        "Data inizio validita": "", 
        "Data prevista fine lavori": "", 
        "Dettaglio localizzazione": "", 
        "Latitudine": "40.7512887", 
        "Importo lavori": "186539.95", 
        "Data pubblicazione": "2013-07-23", 
        "Importo totale": "2979233", 
        "Data fine validita": "", 
        "ID bando": "48245", 
        "Importo base asta": "249523.39", 
        "Operatori associati": "", 
        "ID progetto": "16218", 
        "Oneri della sicurezza": "30103.97", 
        "Progetto": "Lavori di ripristino e di consolidamento delle strutture della casa della Fontana Piccola – Pompei Scavi", 
        "IVA": "", 
        "Importo forniture": "0", 
        "Protocollo determina": "21163", 
        "Somme a disposizione dell'amministrazione": "19571.47", 
        "RUP": "Stefania Argenti"
    }, 
    {
        "Data stipula": "", 
        "CIG": "520699015", 
        "ID contratto": "", 
        "Sigla grande progetto": "G.P.P.", 
        "Operatore capogruppo": "", 
        "Tipo gara": "Procedura aperta", 
        "Importo contratto": "", 
        "Longitudine": "14.4896692", 
        "Tipologia": "Diagnosi e monitoraggio", 
        "Durata giorni": "300", 
        "Aliquota forfettaria": "129788.8", 
        "Piano": "Piano della conoscenza", 
        "ID conti appaltatore": "", 
        "Num ditte invitate": "0", 
        "Oggetto": "Affidamento in sei lotti del \"Piano della conoscenza - Servizi di diagnosi e monitoraggio dello stato di conservazione di Pompei\".", 
        "Importo servizi": "5979341", 
        "Data risoluzione": "", 
        "CUP": "", 
        "Num perizia": "31", 
        "Data prevista inizio lavori": "", 
        "Sotto riserva di legge": "", 
        "Data inizio validita": "", 
        "Data prevista fine lavori": "", 
        "Dettaglio localizzazione": "", 
        "Latitudine": "40.7506957", 
        "Importo lavori": "0.0", 
        "Data pubblicazione": "2013-07-24", 
        "Importo totale": "801748685", 
        "Data fine validita": "", 
        "ID bando": "48261", 
        "Importo base asta": "6436971.12", 
        "Operatori associati": "", 
        "ID progetto": "52139", 
        "Oneri della sicurezza": "327841.32", 
        "Progetto": "Lavori per la messa in sicurezza degli apparati decorativi della Casa di Paquio Proculo Regio I ins. 7", 
        "IVA": "", 
        "Importo forniture": "0", 
        "Protocollo determina": "21165", 
        "Somme a disposizione dell'amministrazione": "134739.41", 
        "RUP": "Vega Ingravallo"
    }, 
    {
        "Data stipula": "2013-12-12", 
        "CIG": "5337430A90", 
        "ID contratto": "42970", 
        "Sigla grande progetto": "G.P.P.", 
        "Operatore capogruppo": "Consorzio Nazionale Sicurezza", 
        "Tipo gara": "Affidamento in economia - cottimo fiduciario", 
        "Importo contratto": "", 
        "Longitudine": "14.4989344", 
        "Tipologia": "Sicurezza sito", 
        "Durata giorni": "60", 
        "Aliquota forfettaria": "", 
        "Piano": "PON Sicurezza per lo sviluppo - Obiettivo Convergenza 2007-2013", 
        "ID conti appaltatore": "42969", 
        "Num ditte invitate": "0", 
        "Oggetto": "Stralcio del PON Sicurezza - Sistema videosorveglianza monitoraggio cantieri e aree di stoccaggio", 
        "Importo servizi": "0", 
        "Data risoluzione": "", 
        "CUP": "F69G12000100006", 
        "Num perizia": "1", 
        "Data prevista inizio lavori": "2013-12-12", 
        "Sotto riserva di legge": "true", 
        "Data inizio validita": "", 
        "Data prevista fine lavori": "", 
        "Dettaglio localizzazione": "Aree cantieri, stoccagio e ingressi cantieri scavi Pompei", 
        "Latitudine": "40.7461572", 
        "Importo lavori": "0.0", 
        "Data pubblicazione": "2013-09-24", 
        "Importo totale": "12979969", 
        "Data fine validita": "", 
        "ID bando": "42298", 
        "Importo base asta": "129799.69", 
        "Operatori associati": "", 
        "ID progetto": "42296", 
        "Oneri della sicurezza": "4211.1", 
        "Progetto": "PON Sicurezza per lo sviluppo - Obiettivo Convergenza 2007-2013 - Una nuova sicurezza per il parco archeologico di Pompei - STRALCIO", 
        "IVA": "", 
        "Importo forniture": "125588.59", 
        "Protocollo determina": "Decreto n. 120 del Soprintendente SANP", 
        "Somme a disposizione dell'amministrazione": "0", 
        "RUP": "Alberto Bruni"
    }, 
    {
        "Data stipula": "2013-06-03", 
        "CIG": "ZB20A0B176", 
        "ID contratto": "28636", 
        "Sigla grande progetto": "G.P.P.", 
        "Operatore capogruppo": "Andromeda s.r.l.", 
        "Tipo gara": "Sistema dinamico di acquisizione", 
        "Importo contratto": "15360", 
        "Longitudine": "14.4989344", 
        "Tipologia": "Attività di promozione", 
        "Durata giorni": "30", 
        "Aliquota forfettaria": "0", 
        "Piano": "Piano per la fruizione, il miglioramento dei servizi e della comunicazione", 
        "ID conti appaltatore": "28635", 
        "Num ditte invitate": "3", 
        "Oggetto": "Servizio di consulenza, supporto operativo, tecnico e logistico per la realizzazione del Convegno \"Moenia e urbs\".", 
        "Importo servizi": "15360", 
        "Data risoluzione": "", 
        "CUP": "", 
        "Num perizia": "1", 
        "Data prevista inizio lavori": "2013-06-05", 
        "Sotto riserva di legge": "false", 
        "Data inizio validita": "", 
        "Data prevista fine lavori": "2013-06-08", 
        "Dettaglio localizzazione": "", 
        "Latitudine": "40.7461572", 
        "Importo lavori": "0.0", 
        "Data pubblicazione": "2013-05-23", 
        "Importo totale": "185856", 
        "Data fine validita": "", 
        "ID bando": "28528", 
        "Importo base asta": "20000", 
        "Operatori associati": "", 
        "ID progetto": "28446", 
        "Oneri della sicurezza": "0", 
        "Progetto": "Realizzazione del Convegno \"Moenia e Urbs\"", 
        "IVA": "3225.6", 
        "Importo forniture": "0", 
        "Protocollo determina": "", 
        "Somme a disposizione dell'amministrazione": "0", 
        "RUP": "Luisa Rapone"
    }, 
    {
        "Data stipula": "", 
        "CIG": "517698030B", 
        "ID contratto": "", 
        "Sigla grande progetto": "G.P.P.", 
        "Operatore capogruppo": "", 
        "Tipo gara": "Procedura aperta", 
        "Importo contratto": "", 
        "Longitudine": "14.4928699", 
        "Tipologia": "Restauro apparati decorativi", 
        "Durata giorni": "210", 
        "Aliquota forfettaria": "15297.31", 
        "Piano": "Piano delle opere", 
        "ID conti appaltatore": "", 
        "Num ditte invitate": "0", 
        "Oggetto": "", 
        "Importo servizi": "0", 
        "Data risoluzione": "", 
        "CUP": "F64B12000370006", 
        "Num perizia": "30", 
        "Data prevista inizio lavori": "", 
        "Sotto riserva di legge": "", 
        "Data inizio validita": "", 
        "Data prevista fine lavori": "", 
        "Dettaglio localizzazione": "", 
        "Latitudine": "40.7518483", 
        "Importo lavori": "657351.04", 
        "Data pubblicazione": "2013-07-06", 
        "Importo totale": "98634192", 
        "Data fine validita": "", 
        "ID bando": "48233", 
        "Importo base asta": "657351.04", 
        "Operatori associati": "", 
        "ID progetto": "16223", 
        "Oneri della sicurezza": "14769.02", 
        "Progetto": "Restauro apparati decorativi della Casa di Venere in Conchiglia in Pompei", 
        "IVA": "", 
        "Importo forniture": "0", 
        "Protocollo determina": "20623", 
        "Somme a disposizione dell'amministrazione": "142510.26", 
        "RUP": "Anna Maria Sodo"
    }, 
    {
        "Data stipula": "2013-11-06", 
        "CIG": "410706486C", 
        "ID contratto": "31394", 
        "Sigla grande progetto": "G.P.P.", 
        "Operatore capogruppo": "Forte Costruzioni e Restauri", 
        "Tipo gara": "Procedura ristretta", 
        "Importo contratto": "192298.52", 
        "Longitudine": "14.4869854", 
        "Tipologia": "Restauro architettonico", 
        "Durata giorni": "275", 
        "Aliquota forfettaria": "", 
        "Piano": "Piano delle opere", 
        "ID conti appaltatore": "31375", 
        "Num ditte invitate": "40", 
        "Oggetto": "", 
        "Importo servizi": "0", 
        "Data risoluzione": "", 
        "CUP": "F64B12000080001", 
        "Num perizia": "13", 
        "Data prevista inizio lavori": "2013-07-18", 
        "Sotto riserva di legge": "true", 
        "Data inizio validita": "", 
        "Data prevista fine lavori": "2014-04-19", 
        "Dettaglio localizzazione": "", 
        "Latitudine": "40.7489221", 
        "Importo lavori": "170377.92", 
        "Data pubblicazione": "2012-04-03", 
        "Importo totale": "32231267", 
        "Data fine validita": "", 
        "ID bando": "16800", 
        "Importo base asta": "192298.52", 
        "Operatori associati": "", 
        "ID progetto": "16216", 
        "Oneri della sicurezza": "3687.88", 
        "Progetto": "Restauro architettonico e messa in sicurezza della Casa delle Pareti Rosse", 
        "IVA": "", 
        "Importo forniture": "18232.72", 
        "Protocollo determina": "13206", 
        "Somme a disposizione dell'amministrazione": "74075.59", 
        "RUP": "Ernesto De Carolis"
    }, 
    {
        "Data stipula": "2013-05-14", 
        "CIG": "4106773848", 
        "ID contratto": "21380", 
        "Sigla grande progetto": "G.P.P.", 
        "Operatore capogruppo": "Perillo Costruzioni Generali", 
        "Tipo gara": "Procedura ristretta", 
        "Importo contratto": "702197.56", 
        "Longitudine": "14.4837588", 
        "Tipologia": "Restauro architettonico", 
        "Durata giorni": "730", 
        "Aliquota forfettaria": "", 
        "Piano": "Piano delle opere", 
        "ID conti appaltatore": "21352,48827,55528", 
        "Num ditte invitate": "22", 
        "Oggetto": "", 
        "Importo servizi": "0", 
        "Data risoluzione": "", 
        "CUP": "F64B12000100001", 
        "Num perizia": "12", 
        "Data prevista inizio lavori": "2013-02-04", 
        "Sotto riserva di legge": "true", 
        "Data inizio validita": "", 
        "Data prevista fine lavori": "2015-02-04", 
        "Dettaglio localizzazione": "Casa dei Dioscuri", 
        "Latitudine": "40.7517468", 
        "Importo lavori": "1430700.24", 
        "Data pubblicazione": "2012-04-03", 
        "Importo totale": "205042591", 
        "Data fine validita": "", 
        "ID bando": "18302", 
        "Importo base asta": "1447735.45", 
        "Operatori associati": "", 
        "ID progetto": "16215", 
        "Oneri della sicurezza": "17035.21", 
        "Progetto": "Restauro architettonico e strutturale Casa dei Dioscuri", 
        "IVA": "147461.49", 
        "Importo forniture": "0", 
        "Protocollo determina": "13208", 
        "Somme a disposizione dell'amministrazione": "0", 
        "RUP": "Ernesto De Carolis"
    }, 
    {
        "Data stipula": "2014-04-01", 
        "CIG": "5177088C28", 
        "ID contratto": "50027", 
        "Sigla grande progetto": "G.P.P.", 
        "Operatore capogruppo": "C.B.C. CONSERVAZIONE BENI CULTURALI", 
        "Tipo gara": "PROCEDURA APERTA EX ARTT. 55, COMMA 5, E 122 DEL DECRETO LEGISLATIVO 12 APRILE 2006 n. 163", 
        "Importo contratto": "", 
        "Longitudine": "14.4923972", 
        "Tipologia": "Restauro apparati decorativi", 
        "Durata giorni": "210", 
        "Aliquota forfettaria": "15297.31", 
        "Piano": "Piano delle opere", 
        "ID conti appaltatore": "49840,54952", 
        "Num ditte invitate": "0", 
        "Oggetto": "", 
        "Importo servizi": "0", 
        "Data risoluzione": "", 
        "CUP": "F64B12000380006", 
        "Num perizia": "17", 
        "Data prevista inizio lavori": "", 
        "Sotto riserva di legge": "true", 
        "Data inizio validita": "", 
        "Data prevista fine lavori": "", 
        "Dettaglio localizzazione": "", 
        "Latitudine": "40.7517423", 
        "Importo lavori": "461215.21", 
        "Data pubblicazione": "2013-07-06", 
        "Importo totale": "69192256", 
        "Data fine validita": "", 
        "ID bando": "47947", 
        "Importo base asta": "461215.21", 
        "Operatori associati": "Consorzio Arkè", 
        "ID progetto": "16207", 
        "Oneri della sicurezza": "8568.87", 
        "Progetto": "Restauro degli apparati decorativi pittorici e pavimentali della Casa di D.Octavius Quartio detta anche Loreio Tiburtino", 
        "IVA": "", 
        "Importo forniture": "0", 
        "Protocollo determina": "20622", 
        "Somme a disposizione dell'amministrazione": "110621.61", 
        "RUP": "Anna Maria Sodo"
    }
]